typing_extensions.py
typing_extensions_qpython-4.12.2.1.dist-info/METADATA
typing_extensions_qpython-4.12.2.1.dist-info/WHEEL
typing_extensions_qpython-4.12.2.1.dist-info/top_level.txt
typing_extensions_qpython-4.12.2.1.dist-info/RECORD
