Metadata-Version: 2.4
Name: typing-extensions-qpython
Version: 4.12.2.1
Summary: Backported and Experimental Type Hints for Python 3.12
Author-email: The QPYPI Team <qpypi@qpython.org>
License: Python Software Foundation License
Project-URL: Homepage, https://qpypi.qpython.org/project/typing-extensions-qpython/
Classifier: Intended Audience :: Developers
Classifier: Intended Audience :: Education
Classifier: Intended Audience :: Information Technology
Classifier: Intended Audience :: End Users/Desktop
Classifier: License :: OSI Approved :: Apache Software License
Classifier: Operating System :: Android
Classifier: Programming Language :: Python
Classifier: Programming Language :: Python :: 3.12
Classifier: Topic :: Software Development
Requires-Python: ==3.12.*
Requires-Dist: greenlet-qpython>=3.1.1
